{
  "region": "europe",
  "region_label": "Europa",
  "flag": "EU",
  "currency": "EUR",
  "phase": "screen",
  "generated_at": "2026-06-25T09:48:12.092097+00:00",
  "generated_at_local": "25.06.2026, 11:48 Uhr",
  "session_date": "2026-06-25",
  "favorite": "RHM.DE",
  "watchlist": [
    {
      "ticker": "RHM.DE",
      "name": "Rheinmetall",
      "last_price": 925.0,
      "previous_close": 949.0,
      "change_pct": -2.53,
      "volume": 201100,
      "avg_volume": 285643,
      "rel_volume": 0.7,
      "score": 1.78,
      "sma20": 1169.89,
      "trend_up": false,
      "session_date": "2026-06-25",
      "news": {
        "sentiment": "negativ",
        "direction": "ab",
        "materiality": "hoch",
        "catalyst": true,
        "summary": "Deutschland bricht Großprojekt für Fregatten ab; Rheinmetall fällt 14% nach Streichung des Mega-Kriegsschiff-Programms.",
        "headline": "Stocks to Watch: Cerebras, Rheinmetall, Micron",
        "url": "https://www.wsj.com/livecoverage/stock-market-today-dow-sp-500-nasdaq-06-24-2026/card/stocks-to-watch-cerebras-rheinmetall-micron-FQBhWg4vxTgEOmUqL8Is?siteid=yhoof2&yptr=yahoo"
      },
      "or_window_min": 5
    },
    {
      "ticker": "VOW3.DE",
      "name": "Volkswagen",
      "last_price": 77.92,
      "previous_close": 76.02,
      "change_pct": 2.5,
      "volume": 443053,
      "avg_volume": 981248,
      "rel_volume": 0.45,
      "score": 1.13,
      "sma20": 85.89,
      "trend_up": false,
      "session_date": "2026-06-25",
      "news": {
        "sentiment": "neutral",
        "direction": "unklar",
        "materiality": "mittel",
        "catalyst": true,
        "summary": "VW verkauft Mehrheitsbeteiligung in Marine-Engine-Unit an Bain Capital; strategische Umstrukturierung.",
        "headline": "Struggling VW to sell majority stake in marine engine unit",
        "url": "https://finance.yahoo.com/markets/stocks/articles/struggling-vw-sell-majority-stake-090930926.html"
      },
      "or_window_min": 15
    },
    {
      "ticker": "IFX.DE",
      "name": "Infineon",
      "last_price": 83.42,
      "previous_close": 79.56,
      "change_pct": 4.85,
      "volume": 1183343,
      "avg_volume": 6331994,
      "rel_volume": 0.19,
      "score": 0.91,
      "sma20": 80.82,
      "trend_up": true,
      "session_date": "2026-06-25",
      "news": {
        "sentiment": "positiv",
        "direction": "auf",
        "materiality": "mittel",
        "catalyst": false,
        "summary": "Infineon profitiert von AI-Rally durch starke Micron-Prognose, wird aber durch China-Patentstreit belastet.",
        "headline": "European shares gain as upbeat Micron forecast revives AI rally",
        "url": "https://finance.yahoo.com/markets/stocks/articles/european-shares-gain-upbeat-micron-072325645.html"
      },
      "or_window_min": 15
    },
    {
      "ticker": "ASML.AS",
      "name": "ASML",
      "last_price": 1615.6,
      "previous_close": 1553.8,
      "change_pct": 3.98,
      "volume": 152661,
      "avg_volume": 736752,
      "rel_volume": 0.21,
      "score": 0.82,
      "sma20": 1550.57,
      "trend_up": true,
      "session_date": "2026-06-25",
      "news": {
        "sentiment": "positiv",
        "direction": "auf",
        "materiality": "mittel",
        "catalyst": false,
        "summary": "ASML partizipiert an globalem Chip-Rally getrieben durch Micron-Rekordergebnisse und AI-Nachfrage.",
        "headline": "European shares gain as upbeat Micron forecast revives AI rally",
        "url": "https://finance.yahoo.com/markets/stocks/articles/european-shares-gain-upbeat-micron-072325645.html"
      },
      "or_window_min": 15
    },
    {
      "ticker": "ADS.DE",
      "name": "Adidas",
      "last_price": 180.15,
      "previous_close": 176.0,
      "change_pct": 2.36,
      "volume": 202661,
      "avg_volume": 690745,
      "rel_volume": 0.29,
      "score": 0.69,
      "sma20": 170.7,
      "trend_up": true,
      "session_date": "2026-06-25",
      "news": {
        "sentiment": "neutral",
        "direction": "unklar",
        "materiality": "gering",
        "catalyst": false,
        "summary": "Unspezifische Schlagzeile zu WM-Effekt auf Sporteinzelhandelsumsätze ohne konkrete Adidas-Relevanz.",
        "headline": "The World Cup effect on sports retail sales",
        "url": "https://www.retail-insight-network.com/news/the-world-cup-effect-on-sports-retail-sales/"
      },
      "or_window_min": 15
    },
    {
      "ticker": "ENR.DE",
      "name": "Siemens Energy",
      "last_price": 162.46,
      "previous_close": 159.86,
      "change_pct": 1.63,
      "volume": 475395,
      "avg_volume": 2648189,
      "rel_volume": 0.18,
      "score": 0.29,
      "sma20": 158.55,
      "trend_up": true,
      "session_date": "2026-06-25",
      "news": null,
      "or_window_min": 15
    },
    {
      "ticker": "BAS.DE",
      "name": "BASF",
      "last_price": 48.21,
      "previous_close": 48.89,
      "change_pct": -1.4,
      "volume": 374095,
      "avg_volume": 2672275,
      "rel_volume": 0.14,
      "score": 0.2,
      "sma20": 49.49,
      "trend_up": false,
      "session_date": "2026-06-25",
      "news": null,
      "or_window_min": 15
    },
    {
      "ticker": "DHL.DE",
      "name": "DHL Group",
      "last_price": 52.2,
      "previous_close": 51.18,
      "change_pct": 1.99,
      "volume": 205394,
      "avg_volume": 2053330,
      "rel_volume": 0.1,
      "score": 0.2,
      "sma20": 51.84,
      "trend_up": true,
      "session_date": "2026-06-25",
      "news": {
        "sentiment": "neutral",
        "direction": "unklar",
        "materiality": "gering",
        "catalyst": false,
        "summary": "FedEx-Zollrückerstattung hat keine direkte Relevanz für DHL Group.",
        "headline": "FedEx to Return $800 Million in Tariff Refunds",
        "url": "https://wwd.com/sourcing-journal/logistics/fedex-return-800-million-tariff-refunds-ieepa-earnings-fuel-surcharges-revenue-iran-war-1239029733/"
      },
      "or_window_min": 15
    },
    {
      "ticker": "SAP.DE",
      "name": "SAP",
      "last_price": 132.7,
      "previous_close": 134.86,
      "change_pct": -1.6,
      "volume": 325302,
      "avg_volume": 3059635,
      "rel_volume": 0.11,
      "score": 0.17,
      "sma20": 147.06,
      "trend_up": false,
      "session_date": "2026-06-25",
      "news": {
        "sentiment": "neutral",
        "direction": "unklar",
        "materiality": "gering",
        "catalyst": false,
        "summary": "Generische Research-Ankündigung ohne konkrete SAP-Nachricht oder Kursbewegungspotential.",
        "headline": "Top Research Reports for Shell, Novo Nordisk & SAP",
        "url": "https://finance.yahoo.com/markets/stocks/articles/top-research-reports-shell-novo-202500776.html"
      },
      "or_window_min": 15
    },
    {
      "ticker": "SIE.DE",
      "name": "Siemens",
      "last_price": 274.6,
      "previous_close": 271.4,
      "change_pct": 1.18,
      "volume": 144867,
      "avg_volume": 1105467,
      "rel_volume": 0.13,
      "score": 0.15,
      "sma20": 270.79,
      "trend_up": true,
      "session_date": "2026-06-25",
      "news": null,
      "or_window_min": 15
    }
  ]
}
