{
  "region": "europe",
  "region_label": "Europa",
  "flag": "EU",
  "currency": "EUR",
  "phase": "screen",
  "generated_at": "2026-06-23T10:07:37.747303+00:00",
  "generated_at_local": "23.06.2026, 12:07 Uhr",
  "session_date": "2026-06-23",
  "favorite": "ASML.AS",
  "watchlist": [
    {
      "ticker": "ASML.AS",
      "name": "ASML",
      "last_price": 1573.5,
      "previous_close": 1655.8,
      "change_pct": -4.97,
      "volume": 230613,
      "avg_volume": 732947,
      "rel_volume": 0.31,
      "score": 1.56,
      "sma20": 1531.1,
      "trend_up": true,
      "session_date": "2026-06-23",
      "news": {
        "sentiment": "negativ",
        "direction": "ab",
        "materiality": "mittel",
        "catalyst": false,
        "summary": "Chip-Sektor unter Druck durch Zinserhöhungs- und KI-Bewertungssorgen, positive Einzelkommentare ändern nichts am negativen Markttrend.",
        "headline": "Global chip stocks slump as rate and AI valuation fears trigger tech selloff",
        "url": "https://finance.yahoo.com/technology/articles/global-chip-stocks-slump-rate-091128932.html"
      },
      "or_window_min": 15
    },
    {
      "ticker": "ENR.DE",
      "name": "Siemens Energy",
      "last_price": 160.36,
      "previous_close": 169.14,
      "change_pct": -5.19,
      "volume": 762323,
      "avg_volume": 2690347,
      "rel_volume": 0.28,
      "score": 1.47,
      "sma20": 159.38,
      "trend_up": true,
      "session_date": "2026-06-23",
      "news": null,
      "or_window_min": 15
    },
    {
      "ticker": "IFX.DE",
      "name": "Infineon",
      "last_price": 81.76,
      "previous_close": 85.94,
      "change_pct": -4.86,
      "volume": 1433860,
      "avg_volume": 6491794,
      "rel_volume": 0.22,
      "score": 1.07,
      "sma20": 80.58,
      "trend_up": true,
      "session_date": "2026-06-23",
      "news": {
        "sentiment": "negativ",
        "direction": "ab",
        "materiality": "mittel",
        "catalyst": false,
        "summary": "Chip-Sektor leidet unter breiter Tech-Sell-off ausgelöst durch Zinserhöhungsfurcht und Bewertungsangst.",
        "headline": "Global chip stocks slump as rate and AI valuation fears trigger tech selloff",
        "url": "https://finance.yahoo.com/technology/articles/global-chip-stocks-slump-rate-091128932.html"
      },
      "or_window_min": 15
    },
    {
      "ticker": "VOW3.DE",
      "name": "Volkswagen",
      "last_price": 78.26,
      "previous_close": 80.32,
      "change_pct": -2.56,
      "volume": 364704,
      "avg_volume": 950548,
      "rel_volume": 0.38,
      "score": 0.98,
      "sma20": 87.46,
      "trend_up": false,
      "session_date": "2026-06-23",
      "news": {
        "sentiment": "neutral",
        "direction": "unklar",
        "materiality": "gering",
        "catalyst": false,
        "summary": "Porsche-CEO bestätigt Ausblick trotz Herausforderungen; News zu Himax ohne Relevanz für VW.",
        "headline": "Porsche CEO confirms forecast despite persistent challenges, speech text shows",
        "url": "https://ca.finance.yahoo.com/news/porsche-ceo-confirms-forecast-despite-165054231.html"
      },
      "or_window_min": 15
    },
    {
      "ticker": "DTE.DE",
      "name": "Deutsche Telekom",
      "last_price": 26.54,
      "previous_close": 26.12,
      "change_pct": 1.61,
      "volume": 1948566,
      "avg_volume": 7465785,
      "rel_volume": 0.26,
      "score": 0.42,
      "sma20": 27.86,
      "trend_up": false,
      "session_date": "2026-06-23",
      "news": null,
      "or_window_min": 15
    },
    {
      "ticker": "SIE.DE",
      "name": "Siemens",
      "last_price": 272.4,
      "previous_close": 279.0,
      "change_pct": -2.37,
      "volume": 185961,
      "avg_volume": 1113617,
      "rel_volume": 0.17,
      "score": 0.4,
      "sma20": 270.78,
      "trend_up": true,
      "session_date": "2026-06-23",
      "news": {
        "sentiment": "positiv",
        "direction": "auf",
        "materiality": "mittel",
        "catalyst": false,
        "summary": "US-KI-Beschränkungen fördern europäische Firmen als Alternative, was Siemens strategisch begünstigt.",
        "headline": "US curbs on AI spur European firms to spread the risk",
        "url": "https://finance.yahoo.com/technology/ai/articles/analysis-us-curbs-ai-spur-105732699.html"
      },
      "or_window_min": 15
    },
    {
      "ticker": "SAP.DE",
      "name": "SAP",
      "last_price": 134.58,
      "previous_close": 132.22,
      "change_pct": 1.78,
      "volume": 629697,
      "avg_volume": 3151890,
      "rel_volume": 0.2,
      "score": 0.36,
      "sma20": 148.76,
      "trend_up": false,
      "session_date": "2026-06-23",
      "news": null,
      "or_window_min": 15
    },
    {
      "ticker": "DBK.DE",
      "name": "Deutsche Bank",
      "last_price": 31.02,
      "previous_close": 31.5,
      "change_pct": -1.52,
      "volume": 1033907,
      "avg_volume": 5460649,
      "rel_volume": 0.19,
      "score": 0.29,
      "sma20": 28.78,
      "trend_up": true,
      "session_date": "2026-06-23",
      "news": {
        "sentiment": "neutral",
        "direction": "unklar",
        "materiality": "gering",
        "catalyst": false,
        "summary": "Bankkommentare zu Märkten und Fed sind analytisch, nicht transaktionsrelevant; Gold-Decline betrifft DB nicht wesentlich.",
        "headline": "Gold Slumps as Tech Selloff Reverberates Through Global Markets",
        "url": "https://finance.yahoo.com/markets/commodities/articles/gold-steadies-us-iran-flag-000701656.html"
      },
      "or_window_min": 15
    },
    {
      "ticker": "MUV2.DE",
      "name": "Munich Re",
      "last_price": 471.5,
      "previous_close": 478.0,
      "change_pct": -1.36,
      "volume": 86009,
      "avg_volume": 410121,
      "rel_volume": 0.21,
      "score": 0.29,
      "sma20": 457.98,
      "trend_up": true,
      "session_date": "2026-06-23",
      "news": null,
      "or_window_min": 15
    },
    {
      "ticker": "BAS.DE",
      "name": "BASF",
      "last_price": 48.28,
      "previous_close": 49.17,
      "change_pct": -1.82,
      "volume": 398073,
      "avg_volume": 2705917,
      "rel_volume": 0.15,
      "score": 0.27,
      "sma20": 49.69,
      "trend_up": false,
      "session_date": "2026-06-23",
      "news": null,
      "or_window_min": 15
    }
  ]
}
